Workbook

Sheet Instrucciones
A1: Hojas de trabajo: El dinero de mi negocio
A2: Celdas amarillas: escriba sus datos. Celdas verdes: se calculan solas.
A3: Los datos que trae el archivo son del caso Dulce Canela (repostería, pequeño contribuyente). Reemplácelos por los suyos.
A4: Impuestos: escriba el porcentaje que corresponde a SU régimen. Ejemplo del caso: 5 % sobre ingresos brutos (pequeño contribuyente, Ley del IVA art. 47).
A5: Si está en el régimen general del IVA, use precios SIN IVA para costos y ventas, ponga 0 % en 'impuesto sobre la venta' y 12 % en 'IVA que se agrega al precio'.
A6: El ISR no se suma al precio como recargo: depende de su régimen. Confirme con su contador.
A7: Este material es de educación financiera básica y no sustituye la orientación de un contador.

Sheet 1 Registro
A1: Hoja 1. Registro diario de entradas y salidas
A2: Tipo: V venta contado · C cobro venta anterior · I insumos · F gasto fijo · T traslado a reserva de impuestos · P pago de impuesto · R retiro personal · O otro
A3: Saldo inicial | B3: 2500
A5: Fecha | B5: Concepto | C5: Tipo | D5: Entrada (Q) | E5: Salida (Q) | F5: Saldo (Q)
A6: 01/mes | B6: Ventas al contado del día | C6: V | D6: 640 | F6: =IF(AND(D6="",E6=""),"",N($B$3)+N(D6)-N(E6))
A7: 01/mes | B7: Pago de alquiler | C7: F | E7: 1800 | F7: =IF(AND(D7="",E7=""),"",N(F6)+N(D7)-N(E7))
A8: 02/mes | B8: Compra de harina, huevos y mantequilla | C8: I | E8: 650 | F8: =IF(AND(D8="",E8=""),"",N(F7)+N(D8)-N(E8))
A9: 03/mes | B9: Ventas al contado del día | C9: V | D9: 800 | F9: =IF(AND(D9="",E9=""),"",N(F8)+N(D9)-N(E9))
A10: 04/mes | B10: Traslado al sobre de impuestos | C10: T | E10: 200 | F10: =IF(AND(D10="",E10=""),"",N(F9)+N(D10)-N(E10))
A11: 05/mes | B11: Retiro para gastos de la casa | C11: R | E11: 600 | F11: =IF(AND(D11="",E11=""),"",N(F10)+N(D11)-N(E11))
F12: =IF(AND(D12="",E12=""),"",N(F11)+N(D12)-N(E12))
F13: =IF(AND(D13="",E13=""),"",N(F12)+N(D13)-N(E13))
F14: =IF(AND(D14="",E14=""),"",N(F13)+N(D14)-N(E14))
F15: =IF(AND(D15="",E15=""),"",N(F14)+N(D15)-N(E15))
F16: =IF(AND(D16="",E16=""),"",N(F15)+N(D16)-N(E16))
F17: =IF(AND(D17="",E17=""),"",N(F16)+N(D17)-N(E17))
F18: =IF(AND(D18="",E18=""),"",N(F17)+N(D18)-N(E18))
F19: =IF(AND(D19="",E19=""),"",N(F18)+N(D19)-N(E19))
F20: =IF(AND(D20="",E20=""),"",N(F19)+N(D20)-N(E20))
F21: =IF(AND(D21="",E21=""),"",N(F20)+N(D21)-N(E21))
F22: =IF(AND(D22="",E22=""),"",N(F21)+N(D22)-N(E22))
F23: =IF(AND(D23="",E23=""),"",N(F22)+N(D23)-N(E23))
... F45: =IF(AND(D45="",E45=""),"",N(F44)+N(D45)-N(E45))
B47: Total entradas | D47: =SUM(D6:D45)
B48: Total salidas | D48: =SUM(E6:E45)
B49: De las salidas: retiros personales (R) | D49: =SUMIF(C6:C45,"R",E6:E45)
B50: De las salidas: traslados a reserva de impuestos (T) | D50: =SUMIF(C6:C45,"T",E6:E45)
B51: Saldo final | D51: =B3+SUM(D6:D45)-SUM(E6:E45)
B53: Nota: llene las filas en orden, sin dejar filas vacías en medio, para que el saldo de cada fila sea correcto.

Sheet 2 Costo
A1: Hoja 2. Costo de mi producto o servicio
A2: Producto del ejemplo: pastel mediano de chocolate (Dulce Canela). Valores con IVA incluido porque es pequeño contribuyente.
A4: A. Costo variable: insumo o material | B4: Costo por unidad (Q)
A5: Harina | B5: 6
A6: Azúcar | B6: 5
A7: Huevos | B7: 9
A8: Mantequilla | B8: 10
A9: Chocolate y cacao | B9: 10
A10: Leche y otros | B10: 2
A11: Caja y base de cartón | B11: 6
A12: Gas del horno | B12: 4
A15: Costo variable por unidad (A) | B15: =SUM(B5:B14)
A17: B. Costos fijos del mes | B17: Q al mes
A18: Alquiler | B18: 1800
A19: Ayudante | B19: 1200
A20: Luz y agua | B20: 400
A21: Internet y teléfono | B21: 250
A22: Publicidad | B22: 350
A23: Ahorro para reponer equipo | B23: 300
A24: Sueldo del dueño | B24: 2700
A25: Otros
A26: Total costos fijos (B) | B26: =SUM(B18:B25)
A28: Unidades que vendo al mes (C) | B28: 100
A29: Costo fijo por unidad = B ÷ C | B29: =IF(B28>0,B26/B28,0)
A30: Costo total por unidad = A + B ÷ C | B30: =B15+B29

Sheet 3 Precio
A1: Hoja 3. Revisión de mi precio
A2: Pequeño contribuyente: impuesto sobre la venta 5 %, IVA agregado 0 %. Régimen general: impuesto sobre la venta 0 %, IVA agregado 12 % (costos sin IVA).
A4: Costo variable por unidad | B4: ='2 Costo'!B15
A5: Costo fijo por unidad | B5: ='2 Costo'!B29
A6: Costo total por unidad | B6: =B4+B5
A7: Ganancia que quiero por unidad | B7: 30
A8: % impuesto sobre la venta que paga el negocio (según su régimen) | B8: 0.05
A9: % IVA que se agrega al precio del cliente (régimen general) | B9: 0
A10: Precio sugerido antes de IVA agregado = (costo total + ganancia) ÷ (1 − impuesto) | B10: =(B6+B7)/(1-B8)
A11: PRECIO SUGERIDO AL CLIENTE | B11: =B10*(1+B9)
A12: IVA incluido en ese precio (no es ingreso del negocio) | B12: =B10*B9
A14: Mi precio actual al cliente | B14: 160
A15: Precio actual sin IVA agregado | B15: =B14/(1+B9)
A16: Impuesto sobre la venta de mi precio actual | B16: =B15*B8
A17: Margen de contribución por unidad = precio sin IVA − impuesto − costo variable | B17: =B15-B16-B4
A18: Ganancia por unidad (con las unidades de la Hoja 2) | B18: =B17-B5
A19: ¿Mi precio cubre el sugerido? | B19: =IF(B14>=B11-0.005,"Sí","No: revise costos o precio")
A21: El ISR no se suma aquí como recargo. Verifique que la ganancia elegida alcance para el ISR que corresponda a su régimen.

Sheet 4 Equilibrio
A1: Hoja 4. Mi punto de equilibrio
A2: Forma 1 toma los datos de las hojas 2 y 3. Forma 2 sirve si vende muchos productos.
A4: Forma 1: un producto principal
A5: Costos fijos del mes | B5: ='2 Costo'!B26
A6: Margen de contribución por unidad | B6: ='3 Precio'!B17
A7: Punto de equilibrio (exacto) | B7: =IF(B6>0,B5/B6,0)
A8: Punto de equilibrio en unidades (redondeado hacia arriba) | B8: =ROUNDUP(B7,0)
A9: Punto de equilibrio en quetzales (unidades × precio al cliente) | B9: =B8*'3 Precio'!B14
A10: Unidades por semana (÷ 4) | B10: =ROUNDUP(B8/4,0)
A12: Forma 2: muchos productos
A13: Ventas del mes (sin IVA agregado) | B13: 16000
A14: Impuesto sobre ventas del mes (si aplica) | B14: 800
A15: Costos variables del mes | B15: 5200
A16: Margen de contribución del mes | B16: =B13-B14-B15
A17: % de margen = margen ÷ ventas | B17: =IF(B13>0,B16/B13,0)
A18: Costos fijos del mes | B18: 7000
A19: Ventas de equilibrio = costos fijos ÷ % de margen | B19: =IF(B17>0,B18/B17,0)

Sheet 5 Flujo semanal
A1: Hoja 5. Plan semanal de efectivo
A2: Ejemplo: Dulce Canela. Saldo final = saldo inicial + entradas − salidas. La reserva de impuestos no se usa para cubrir faltantes.
A4: Concepto | B4: Semana 1 | C4: Semana 2 | D4: Semana 3 | E4: Semana 4
A5: Saldo inicial | B5: 2500 | C5: =B20 | D5: =C20 | E5: =D20
A6: Cobros al contado | B6: 3200 | C6: 3200 | D6: 3200 | E6: 3200
A7: Cobros de ventas al crédito | B7: 0 | C7: 3200 | D7: 0 | E7: 0
A8: Otras entradas (préstamo, aporte) | B8: 0 | C8: 0 | D8: 0 | E8: 0
A9: Total entradas | B9: =SUM(B6:B8) | C9: =SUM(C6:C8) | D9: =SUM(D6:D8) | E9: =SUM(E6:E8)
A10: Insumos | B10: 1300 | C10: 1300 | D10: 1300 | E10: 1300
A11: Alquiler | B11: 1800 | C11: 0 | D11: 0 | E11: 0
A12: Sueldos y pagos a ayudantes | B12: 300 | C12: 300 | D12: 300 | E12: 300
A13: Servicios (luz, agua, internet) | B13: 0 | C13: 250 | D13: 400 | E13: 0
A14: Publicidad y otros gastos | B14: 350 | C14: 0 | D14: 0 | E14: 0
A15: Cuotas de préstamos | B15: 0 | C15: 0 | D15: 0 | E15: 0
A16: Mi sueldo (retiro del dueño) | B16: 0 | C16: 1350 | D16: 0 | E16: 1350
A17: Ahorro para equipo o imprevistos | B17: 0 | C17: 0 | D17: 0 | E17: 300
A18: Traslado a reserva de impuestos | B18: 200 | C18: 200 | D18: 200 | E18: 200
A19: Total salidas | B19: =SUM(B10:B18) | C19: =SUM(C10:C18) | D19: =SUM(D10:D18) | E19: =SUM(E10:E18)
A20: Saldo final | B20: =B5+B9-B19 | C20: =C5+C9-C19 | D20: =D5+D9-D19 | E20: =E5+E9-E19
A22: Alerta | B22: =IF(B20<0,"¡FALTANTE!","OK") | C22: =IF(C20<0,"¡FALTANTE!","OK") | D22: =IF(D20<0,"¡FALTANTE!","OK") | E22: =IF(E20<0,"¡FALTANTE!","OK")
A24: Reserva de impuestos
A25: Concepto | B25: Semana 1 | C25: Semana 2 | D25: Semana 3 | E25: Semana 4
A26: Saldo inicial de la reserva | B26: 800 | C26: =B29 | D26: =C29 | E26: =D29
A27: (+) Traslado de la semana | B27: =B18 | C27: =C18 | D27: =D18 | E27: =E18
A28: (−) Pago a la SAT | B28: 0 | C28: 800 | D28: 0 | E28: 0
A29: Saldo final de la reserva | B29: =B26+B27-B28 | C29: =C26+C27-C28 | D29: =D26+D27-D28 | E29: =E26+E27-E28
A31: Ejemplo: el impuesto del mes anterior (Q800) se paga con la reserva, no con el efectivo de operación.
